django_dynamic_from_clause/__init__.py
django_dynamic_from_clause/apps.py
django_dynamic_from_clause/compiler.py
django_dynamic_from_clause/models.py
django_dynamic_from_clause/query.py
django_dynamic_from_clause/sql.py
tests/test_app/__init__.py
tests/test_app/apps.py
tests/test_app/models.py
tests/test_app/migrations/__init__.py
django_dynamic_from_clause-0.0.6.dist-info/LICENSE
django_dynamic_from_clause-0.0.6.dist-info/METADATA
django_dynamic_from_clause-0.0.6.dist-info/WHEEL
django_dynamic_from_clause-0.0.6.dist-info/top_level.txt
django_dynamic_from_clause-0.0.6.dist-info/RECORD
