Metadata-Version: 2.1
Name: django-dynamic-from-clause
Version: 0.0.6
Summary: Gives the ability to dynamically configure SQL For clause for models. This give you ability to wrap any sql into models and use ORM features on it.
Home-page: https://github.com/BezBartek/django-dynamic-from-clause
Author: Bartłomiej Nowak
Author-email: n.bartek3762@gmail.com
License: MIT
Keywords: Django,Django from,From clause,Dynamic from clause,Django table function,Django nested query,Expression to model,Wrap queryset,Dynamic perspective,Evaluate model from queryset
Platform: UNKNOWN
Classifier: License :: OSI Approved :: MIT License
Classifier: Programming Language :: Python :: 3
Classifier: Programming Language :: Python :: 3.7
Classifier: Programming Language :: Python :: 3.8
Classifier: Programming Language :: Python :: 3.9
Classifier: Programming Language :: Python :: 3.10
License-File: LICENSE
Requires-Dist: Django
